randopass/__init__.py
randopass/__main__.py
randopass/randopass.py
randopass/dictionaries/afrikaans.py
randopass/dictionaries/english.py
randopass/dictionaries/english_simple.py
randopass-0.1.6.dist-info/LICENSE
randopass-0.1.6.dist-info/WHEEL
randopass-0.1.6.dist-info/METADATA
randopass-0.1.6.dist-info/RECORD
